mt3scm/__init__.py
mt3scm/mt3scm_computation.py
mt3scm-0.4.8.dist-info/LICENSE
mt3scm-0.4.8.dist-info/WHEEL
mt3scm-0.4.8.dist-info/METADATA
mt3scm-0.4.8.dist-info/RECORD
