Metadata-Version: 2.1
Name: mt3scm
Version: 0.4.8
Summary: Python package for 'Multivariate Time Series Sub-Sequence CLustering Metric'
Home-page: https://github.com/Jokonu/mt3scm
License: BSD-3-Clause
Keywords: time-series,multivariate,clustering,metric,subsequence,curvature
Author: Jonas Köhne
Author-email: jokohonas@gmail.com
Maintainer: Jonas Köhne
Maintainer-email: jokohonas@gmail.com
Requires-Python: >=3.9
Classifier: Environment :: Console
Classifier: Intended Audience :: Science/Research
Classifier: License :: OSI Approved :: BSD License
Classifier: Operating System :: OS Independent
Classifier: Programming Language :: Python :: 3
Classifier: Programming Language :: Python :: 3.10
Classifier: Programming Language :: Python :: 3.9
Classifier: Topic :: Scientific/Engineering
Requires-Dist: numpy (>=1.22.3,<2.0.0)
Requires-Dist: pandas (>=1.4.1,<2.0.0)
Requires-Dist: scikit-learn (>=1.0.2,<2.0.0)
Project-URL: Repository, https://github.com/Jokonu/mt3scm
